rates/__init__.py
rates/config.py
rates/targets.py
rates/architectures/__init__.py
rates/architectures/kernels.py
rates/auxillary/__init__.py
rates/auxillary/dataset.py
rates/auxillary/graphs.py
rates/auxillary/io.py
rates/auxillary/linalg.py
rates/auxillary/loss.py
rates/auxillary/training.py
rates/datasets/__init__.py
rates/datasets/augmentations.py
rates/datasets/circles.py
rates/datasets/halfmoons.py
rates/datasets/mixture.py
rates-0.0.2.dist-info/METADATA
rates-0.0.2.dist-info/WHEEL
rates-0.0.2.dist-info/top_level.txt
rates-0.0.2.dist-info/RECORD
