Metadata-Version: 2.1
Name: rates
Version: 0.0.2
Summary: Research library to study empirical convergence rates.
Author-email: Vivien Cabannes <vivien.cabannes@gmail.com>
Project-URL: Homepage, https://github.com/VivienCabannes/rates
Project-URL: Bug Tracker, https://github.com/VivienCabannes/rates/issues
Classifier: Programming Language :: Python :: 3
Classifier: License :: OSI Approved :: MIT License
Classifier: Operating System :: OS Independent
Requires-Python: >=3.9
Requires-Dist: matplotlib
Requires-Dist: numpy
Requires-Dist: scipy
